<workflow-app name="sqoop-wf" xmlns="uri:oozie:workflow:0.2">
	<start to="sqoop_action_6" />
	
	<action name="sqoop_action_6">
		<sqoop xmlns="uri:oozie:sqoop-action:0.2">
			<job-tracker>${jobTracker}</job-tracker>
			<name-node>${nameNode}</name-node>
			<prepare>
				<delete path="/data/database//rpm/aim_accessories" />
			</prepare>
			<configuration>
				<property>
					<name>mapred.job.queue.name</name>
					<value>${queueName}</value>
				</property>
				<property>
					<name>oozie.hive.defaults</name>
					<value>/tmp/oozie-hive-site.xml</value>
				</property>
			</configuration>
				<arg>import</arg>
				<arg>--connect</arg>
				<arg>${jdbcUrl}</arg>
				<arg>--username</arg>
				<arg>${sqlUser}</arg>
				<arg>--password</arg>
				<arg>${sqlPass}</arg>
				<arg>--table</arg>
				<arg>account_snapshots</arg>
				<arg>--warehouse-dir=/data/database//rpm/</arg>
				<arg>-m</arg>
				<arg>1
</arg>
				<arg>--hive-import</arg>
				<arg>--hive-overwrite</arg>
				<arg>--hive-table</arg>
				<arg>rpm.aim_accessories_stg</arg>
												<file>/tmp/hive-site.xml#hive-site.xml</file>
		</sqoop>
		<ok to="sqoop_action_11" />
		<error to="failEmail" />
	</action>
	
	<action name="sqoop_action_11">
		<sqoop xmlns="uri:oozie:sqoop-action:0.2">
			<job-tracker>${jobTracker}</job-tracker>
			<name-node>${nameNode}</name-node>
			<prepare>
				<delete path="/data/database//rpm/aim_vehicle_locations" />
			</prepare>
			<configuration>
				<property>
					<name>mapred.job.queue.name</name>
					<value>${queueName}</value>
				</property>
				<property>
					<name>oozie.hive.defaults</name>
					<value>/tmp/oozie-hive-site.xml</value>
				</property>
			</configuration>
				<arg>import</arg>
				<arg>--connect</arg>
				<arg>${jdbcUrl}</arg>
				<arg>--username</arg>
				<arg>${sqlUser}</arg>
				<arg>--password</arg>
				<arg>${sqlPass}</arg>
				<arg>--table</arg>
				<arg>account_snapshots</arg>
				<arg>--warehouse-dir=/data/database//rpm/</arg>
				<arg>-m</arg>
				<arg>1
</arg>
				<arg>--hive-import</arg>
				<arg>--hive-overwrite</arg>
				<arg>--hive-table</arg>
				<arg>rpm.aim_vehicle_locations_stg</arg>
												<file>/tmp/hive-site.xml#hive-site.xml</file>
		</sqoop>
		<ok to="sqoop_action_16" />
		<error to="failEmail" />
	</action>
	
	<action name="sqoop_action_16">
		<sqoop xmlns="uri:oozie:sqoop-action:0.2">
			<job-tracker>${jobTracker}</job-tracker>
			<name-node>${nameNode}</name-node>
			<prepare>
				<delete path="/data/database//rpm/background_jobs" />
			</prepare>
			<configuration>
				<property>
					<name>mapred.job.queue.name</name>
					<value>${queueName}</value>
				</property>
				<property>
					<name>oozie.hive.defaults</name>
					<value>/tmp/oozie-hive-site.xml</value>
				</property>
			</configuration>
				<arg>import</arg>
				<arg>--connect</arg>
				<arg>${jdbcUrl}</arg>
				<arg>--username</arg>
				<arg>${sqlUser}</arg>
				<arg>--password</arg>
				<arg>${sqlPass}</arg>
				<arg>--table</arg>
				<arg>account_snapshots</arg>
				<arg>--warehouse-dir=/data/database//rpm/</arg>
				<arg>-m</arg>
				<arg>1
</arg>
				<arg>--hive-import</arg>
				<arg>--hive-overwrite</arg>
				<arg>--hive-table</arg>
				<arg>rpm.background_jobs_stg</arg>
												<file>/tmp/hive-site.xml#hive-site.xml</file>
		</sqoop>
		<ok to="sqoop_action_21" />
		<error to="failEmail" />
	</action>
	
	<action name="sqoop_action_21">
		<sqoop xmlns="uri:oozie:sqoop-action:0.2">
			<job-tracker>${jobTracker}</job-tracker>
			<name-node>${nameNode}</name-node>
			<prepare>
				<delete path="/data/database//rpm/credit_returns" />
			</prepare>
			<configuration>
				<property>
					<name>mapred.job.queue.name</name>
					<value>${queueName}</value>
				</property>
				<property>
					<name>oozie.hive.defaults</name>
					<value>/tmp/oozie-hive-site.xml</value>
				</property>
			</configuration>
				<arg>import</arg>
				<arg>--connect</arg>
				<arg>${jdbcUrl}</arg>
				<arg>--username</arg>
				<arg>${sqlUser}</arg>
				<arg>--password</arg>
				<arg>${sqlPass}</arg>
				<arg>--table</arg>
				<arg>account_snapshots</arg>
				<arg>--warehouse-dir=/data/database//rpm/</arg>
				<arg>-m</arg>
				<arg>1
</arg>
				<arg>--hive-import</arg>
				<arg>--hive-overwrite</arg>
				<arg>--hive-table</arg>
				<arg>rpm.credit_returns_stg</arg>
												<file>/tmp/hive-site.xml#hive-site.xml</file>
		</sqoop>
		<ok to="sqoop_action_26" />
		<error to="failEmail" />
	</action>
	
	<action name="sqoop_action_26">
		<sqoop xmlns="uri:oozie:sqoop-action:0.2">
			<job-tracker>${jobTracker}</job-tracker>
			<name-node>${nameNode}</name-node>
			<prepare>
				<delete path="/data/database//rpm/grounding_users" />
			</prepare>
			<configuration>
				<property>
					<name>mapred.job.queue.name</name>
					<value>${queueName}</value>
				</property>
				<property>
					<name>oozie.hive.defaults</name>
					<value>/tmp/oozie-hive-site.xml</value>
				</property>
			</configuration>
				<arg>import</arg>
				<arg>--connect</arg>
				<arg>${jdbcUrl}</arg>
				<arg>--username</arg>
				<arg>${sqlUser}</arg>
				<arg>--password</arg>
				<arg>${sqlPass}</arg>
				<arg>--table</arg>
				<arg>account_snapshots</arg>
				<arg>--warehouse-dir=/data/database//rpm/</arg>
				<arg>-m</arg>
				<arg>1
</arg>
				<arg>--hive-import</arg>
				<arg>--hive-overwrite</arg>
				<arg>--hive-table</arg>
				<arg>rpm.grounding_users_stg</arg>
												<file>/tmp/hive-site.xml#hive-site.xml</file>
		</sqoop>
		<ok to="sqoop_action_31" />
		<error to="failEmail" />
	</action>
	
	<action name="sqoop_action_31">
		<sqoop xmlns="uri:oozie:sqoop-action:0.2">
			<job-tracker>${jobTracker}</job-tracker>
			<name-node>${nameNode}</name-node>
			<prepare>
				<delete path="/data/database//rpm/marketing_programs_vehicles" />
			</prepare>
			<configuration>
				<property>
					<name>mapred.job.queue.name</name>
					<value>${queueName}</value>
				</property>
				<property>
					<name>oozie.hive.defaults</name>
					<value>/tmp/oozie-hive-site.xml</value>
				</property>
			</configuration>
				<arg>import</arg>
				<arg>--connect</arg>
				<arg>${jdbcUrl}</arg>
				<arg>--username</arg>
				<arg>${sqlUser}</arg>
				<arg>--password</arg>
				<arg>${sqlPass}</arg>
				<arg>--table</arg>
				<arg>account_snapshots</arg>
				<arg>--warehouse-dir=/data/database//rpm/</arg>
				<arg>-m</arg>
				<arg>1
</arg>
				<arg>--hive-import</arg>
				<arg>--hive-overwrite</arg>
				<arg>--hive-table</arg>
				<arg>rpm.marketing_programs_vehicles_stg</arg>
												<file>/tmp/hive-site.xml#hive-site.xml</file>
		</sqoop>
		<ok to="sqoop_action_36" />
		<error to="failEmail" />
	</action>
	
	<action name="sqoop_action_36">
		<sqoop xmlns="uri:oozie:sqoop-action:0.2">
			<job-tracker>${jobTracker}</job-tracker>
			<name-node>${nameNode}</name-node>
			<prepare>
				<delete path="/data/database//rpm/undo_reports" />
			</prepare>
			<configuration>
				<property>
					<name>mapred.job.queue.name</name>
					<value>${queueName}</value>
				</property>
				<property>
					<name>oozie.hive.defaults</name>
					<value>/tmp/oozie-hive-site.xml</value>
				</property>
			</configuration>
				<arg>import</arg>
				<arg>--connect</arg>
				<arg>${jdbcUrl}</arg>
				<arg>--username</arg>
				<arg>${sqlUser}</arg>
				<arg>--password</arg>
				<arg>${sqlPass}</arg>
				<arg>--table</arg>
				<arg>account_snapshots</arg>
				<arg>--warehouse-dir=/data/database//rpm/</arg>
				<arg>-m</arg>
				<arg>1
</arg>
				<arg>--hive-import</arg>
				<arg>--hive-overwrite</arg>
				<arg>--hive-table</arg>
				<arg>rpm.undo_reports_stg</arg>
												<file>/tmp/hive-site.xml#hive-site.xml</file>
		</sqoop>
		<ok to="sqoop_action_41" />
		<error to="failEmail" />
	</action>
	
	<action name="sqoop_action_41">
		<sqoop xmlns="uri:oozie:sqoop-action:0.2">
			<job-tracker>${jobTracker}</job-tracker>
			<name-node>${nameNode}</name-node>
			<prepare>
				<delete path="/data/database//rpm/vehicle_models" />
			</prepare>
			<configuration>
				<property>
					<name>mapred.job.queue.name</name>
					<value>${queueName}</value>
				</property>
				<property>
					<name>oozie.hive.defaults</name>
					<value>/tmp/oozie-hive-site.xml</value>
				</property>
			</configuration>
				<arg>import</arg>
				<arg>--connect</arg>
				<arg>${jdbcUrl}</arg>
				<arg>--username</arg>
				<arg>${sqlUser}</arg>
				<arg>--password</arg>
				<arg>${sqlPass}</arg>
				<arg>--table</arg>
				<arg>account_snapshots</arg>
				<arg>--warehouse-dir=/data/database//rpm/</arg>
				<arg>-m</arg>
				<arg>1
</arg>
				<arg>--hive-import</arg>
				<arg>--hive-overwrite</arg>
				<arg>--hive-table</arg>
				<arg>rpm.vehicle_models_stg</arg>
												<file>/tmp/hive-site.xml#hive-site.xml</file>
		</sqoop>
		<ok to="end" />
		<error to="failEmail" />
	</action>
	<action name="failEmail">
<email xmlns="uri:oozie:email-action:0.1">
<to>${alertEmail}</to>
<subject>oozie job failure</subject>
<body>The workflow ${wf:id()} name ${wf:name()} path ${wf:appPath()} had issues and was killed.  The error message is: ${wf:errorMessage(wf:lastErrorNode())}</body>
</email>
<ok to="fail" />
<error to="fail" />
</action>
<kill name="fail">
<message>Sqoop failed, error message[${wf:errorMessage(wf:lastErrorNode())}]</message>
</kill>
<end name="end" />
</workflow-app>
